README.txt
setup.py
src/zamqp/__init__.py
src/zamqp/_api.py
src/zamqp/_api.txt
src/zamqp/tests.py
src/zamqp.egg-info/PKG-INFO
src/zamqp.egg-info/SOURCES.txt
src/zamqp.egg-info/dependency_links.txt
src/zamqp.egg-info/namespace_packages.txt
src/zamqp.egg-info/not-zip-safe
src/zamqp.egg-info/requires.txt
src/zamqp.egg-info/top_level.txt