Metadata-Version: 1.0
Name: zamqp
Version: 1.0b1
Summary: AMQP broadcasting for python and zope.
Home-page: https://svn.binarybox.net/svn/ztk/zamqp
Author: BlueDynamics Alliance
Author-email: dev@bluedynamics.com
License: GNU General Public Licence
Keywords: amqp events zope
Platform: UNKNOWN
Classifier: Development Status :: 4 - Beta
Classifier: Operating System :: OS Independent
Classifier: Programming Language :: Python
